sunshareclient/__init__.py
sunshareclient/client/__init__.py
sunshareclient/client/api.py
sunshareclient/client/cons.py
sunshareclient/test/test_dataapi.py
sunshareclient/test/__pycache__/test_dataapi.cpython-310.pyc
shihua_sunshareclient-0.1.1.dist-info/LICENSE
shihua_sunshareclient-0.1.1.dist-info/METADATA
shihua_sunshareclient-0.1.1.dist-info/WHEEL
shihua_sunshareclient-0.1.1.dist-info/top_level.txt
shihua_sunshareclient-0.1.1.dist-info/RECORD
