Metadata-Version: 2.1
Name: shihua-sunshareclient
Version: 0.1.1
Summary: SunShareClient is a python sdk with data client
Home-page: https://github.com/redblue0216/SunShareClient
Author: shihua
Author-email: 15021408795@163.com
License: MIT
Requires-Python: >=3.10.9
License-File: LICENSE
